class_proxy
